{
  "topNavbar": [
    {
      "icon": "menu",
      "position": "left",
      "action": "toggleMenu"
    },
    {
      "label": "Majili",
      "position": "center"
    },
    {
      "icon": "account_circle",
      "position": "right",
      "action": "openLogin",
      "route": "/login"
    },
    {
      "icon": "shopping_cart",
      "position": "right",
      "action": "openCart",
      "route": "/cart"
    }
  ],
  "bottomNavbar": [
    {
      "icon": "home",
      "label": "Home",
      "route": "/home",
      "active": true
    },
    {
      "icon": "checkroom",
      "label": "Fashion",
      "route": "/menu"
    },
    {
      "icon": "shopping_cart",
      "label": "Cart",
      "route": "/cart"
    },
    {
      "icon": "inventory",
      "label": "Inventory",
      "route": "/inventory"
    },
    {
      "icon": "receipt",
      "label": "Bill",
      "route": "/invoices"
    },
    {
      "icon": "person",
      "label": "Profile",
      "route": "/profile"
    }
  ],
  "stores": [
    {
      "id": "fashion-store1",
      "name": "Majili Flagship",
      "address": "123 Fashion Avenue, Downtown, City, State 12345",
      "phone": "+1 555 123 4567",
      "hours": "Mon-Sun: 10 AM - 9 PM"
    },
    {
      "id": "fashion-store2",
      "name": "Majili Boutique",
      "address": "456 Style Street, Shopping District, City, State 12345",
      "phone": "+1 555 234 5678",
      "hours": "Mon-Sat: 10 AM - 8 PM, Sun: 12 PM - 6 PM"
    },
    {
      "id": "fashion-store3",
      "name": "Majili Express",
      "address": "789 Trend Lane, Mall Location, City, State 12345",
      "phone": "+1 555 345 6789",
      "hours": "Mon-Sun: 9 AM - 10 PM"
    }
  ]
}

